geoportal/__init__.py
geoportal/cli/extract.py
geoportal/elements/__init__.py
geoportal/elements/input/__init__.py
geoportal/elements/input/geo_checkbox.py
geoportal/elements/input/geo_csv_reader.py
geoportal/elements/input/geo_dropdown.py
geoportal/elements/input/geo_file_input.py
geoportal/elements/input/geo_number_input.py
geoportal/elements/input/geo_radio_button.py
geoportal/elements/input/geo_slider.py
geoportal/elements/input/geo_text_input.py
geoportal/utils/__init__.py
geoportal/utils/output.py
geoportal-1.0.0.dist-info/LICENSE
geoportal-1.0.0.dist-info/METADATA
geoportal-1.0.0.dist-info/WHEEL
geoportal-1.0.0.dist-info/entry_points.txt
geoportal-1.0.0.dist-info/RECORD
